jcsv/__init__.py
jcsv/converter_csv2json.py
jcsv/converter_json2csv.py
jcsv-0.2.19.dist-info/entry_points.txt
jcsv-0.2.19.dist-info/WHEEL
jcsv-0.2.19.dist-info/METADATA
jcsv-0.2.19.dist-info/RECORD
