Metadata-Version: 2.1
Name: jcsv
Version: 0.2.19
Summary: Convert csv to json and convert json to csv 
Author: Deangellis Césari de Oliveira Santiago
Author-email: deangellis1@gmail.com
Requires-Python: >=3.7,<4.0
Classifier: Programming Language :: Python :: 3
Classifier: Programming Language :: Python :: 3.10
Classifier: Programming Language :: Python :: 3.7
Classifier: Programming Language :: Python :: 3.8
Classifier: Programming Language :: Python :: 3.9
Requires-Dist: click (>=8.0.3,<9.0.0)
Requires-Dist: pathlib (>=1.0.1,<2.0.0)
